vpt_segmentation_packing/__init__.py
vpt_segmentation_packing/assemble.py
vpt_segmentation_packing/cellgenerator/__init__.py
vpt_segmentation_packing/cellgenerator/web_cells_generator.py
vpt_segmentation_packing/celltransfer/__init__.py
vpt_segmentation_packing/celltransfer/cell_transfer.py
vpt_segmentation_packing/data/__init__.py
vpt_segmentation_packing/data/polygon_manager.py
vpt_segmentation_packing/data/raw_cell.py
vpt_segmentation_packing/data/web_polygon_manager.py
vpt_segmentation_packing/pack.py
vpt_segmentation_packing/preprocess.py
vpt_segmentation_packing/unpack.py
vpt_segmentation_packing/util/__init__.py
vpt_segmentation_packing/util/convex_hull.py
vpt_segmentation_packing/util/general_data.py
vpt_segmentation_packing/util/io.py
vpt_segmentation_packing/util/unpacking.py
vpt_segmentation_packing/util/vector_operations.py
vpt_segmentation_packing/util/vizwebmanifest.py
vpt_segmentation_packing-1.0.1.dist-info/LICENSE.md
vpt_segmentation_packing-1.0.1.dist-info/METADATA
vpt_segmentation_packing-1.0.1.dist-info/WHEEL
vpt_segmentation_packing-1.0.1.dist-info/RECORD
