Metadata-Version: 2.1
Name: vpt-segmentation-packing
Version: 1.0.1
Summary: Packs cell boundaries for the Vizgen vzg2 file format
Home-page: https://github.com/Vizgen/vpt-segmentation-packing
License: Apache-2.0
Author: Vizgen
Author-email: techsupport@vizgen.com
Maintainer: Timothy Wiggin
Maintainer-email: timothy.wiggin@vizgen.com
Requires-Python: >=3.9,<3.11
Classifier: License :: OSI Approved :: Apache Software License
Classifier: Natural Language :: English
Classifier: Programming Language :: Python :: 3
Classifier: Programming Language :: Python :: 3.9
Classifier: Programming Language :: Python :: 3.10
Classifier: Topic :: Scientific/Engineering :: Bio-Informatics
Requires-Dist: mapbox-earcut (>=1.0.1)
Requires-Dist: numpy (>=1.24.3)
Requires-Dist: pandas[hdf5] (>=2.0.3)
Requires-Dist: pyarrow (>=8.0.0)
Requires-Dist: shapely (>=2.0.0)
Project-URL: Documentation, https://vizgen.github.io/vizgen-postprocessing/
Project-URL: Repository, https://github.com/Vizgen/vpt-segmentation-packing
